Workbook

Sheet Sheet1
A1: Segment | B1: Country | C1: Product | D1: Discount Band | E1: Units Sold | F1: Manufacturing Price | G1: Sale Price | H1: Gross Sales | I1: Discounts | J1: Sales | K1: COGS | L1: Profit | M1: Date | N1: Month Number | O1: Month Name | P1: Year
A2: Government | B2: Canada | C2: Carretera | D2: None | E2: 1618.5 | F2: 3 | G2: 20 | H2: 32370 | I2: 0 | J2: 32370 | K2: 16185 | L2: 16185 | M2: 41640 | N2: 1 | O2: January | P2: 2014
A3: Government | B3: Germany | C3: Carretera | D3: None | E3: 1321 | F3: 3 | G3: 20 | H3: 26420 | I3: 0 | J3: 26420 | K3: 13210 | L3: 13210 | M3: 41640 | N3: 1 | O3: January | P3: 2014
A4: Midmarket | B4: France | C4: Carretera | D4: None | E4: 2178 | F4: 3 | G4: 15 | H4: 32670 | I4: 0 | J4: 32670 | K4: 21780 | L4: 10890 | M4: 41791 | N4: 6 | O4: June | P4: 2014
A5: Midmarket | B5: Germany | C5: Carretera | D5: None | E5: 888 | F5: 3 | G5: 15 | H5: 13320 | I5: 0 | J5: 13320 | K5: 8880 | L5: 4440 | M5: 41791 | N5: 6 | O5: June | P5: 2014
A6: Midmarket | B6: Mexico | C6: Carretera | D6: None | E6: 2470 | F6: 3 | G6: 15 | H6: 37050 | I6: 0 | J6: 37050 | K6: 24700 | L6: 12350 | M6: 41791 | N6: 6 | O6: June | P6: 2014
A7: Government | B7: Germany | C7: Carretera | D7: None | E7: 1513 | F7: 3 | G7: 350 | H7: 529550 | I7: 0 | J7: 529550 | K7: 393380 | L7: 136170 | M7: 41974 | N7: 12 | O7: December | P7: 2014
A8: Midmarket | B8: Germany | C8: Montana | D8: None | E8: 921 | F8: 5 | G8: 15 | H8: 13815 | I8: 0 | J8: 13815 | K8: 9210 | L8: 4605 | M8: 41699 | N8: 3 | O8: March | P8: 2014
A9: Channel Partners | B9: Canada | C9: Montana | D9: None | E9: 2518 | F9: 5 | G9: 12 | H9: 30216 | I9: 0 | J9: 30216 | K9: 7554 | L9: 22662 | M9: 41791 | N9: 6 | O9: June | P9: 2014
A10: Government | B10: France | C10: Montana | D10: None | E10: 1899 | F10: 5 | G10: 20 | H10: 37980 | I10: 0 | J10: 37980 | K10: 18990 | L10: 18990 | M10: 41791 | N10: 6 | O10: June | P10: 2014
A11: Channel Partners | B11: Germany | C11: Montana | D11: None | E11: 1545 | F11: 5 | G11: 12 | H11: 18540 | I11: 0 | J11: 18540 | K11: 4635 | L11: 13905 | M11: 41791 | N11: 6 | O11: June | P11: 2014
A12: Midmarket | B12: Mexico | C12: Montana | D12: None | E12: 2470 | F12: 5 | G12: 15 | H12: 37050 | I12: 0 | J12: 37050 | K12: 24700 | L12: 12350 | M12: 41791 | N12: 6 | O12: June | P12: 2014
A13: Enterprise | B13: Canada | C13: Montana | D13: None | E13: 2665.5 | F13: 5 | G13: 125 | H13: 333187.5 | I13: 0 | J13: 333187.5 | K13: 319860 | L13: 13327.5 | M13: 41821 | N13: 7 | O13: July | P13: 2014
... A701: Channel Partners | B701: United States of America | C701: VTT | D701: High | E701: 1806 | F701: 250 | G701: 12 | H701: 21672 | I701: 3250.8 | J701: 18421.2 | K701: 5418 | L701: 13003.2 | M701: 41760 | N701: 5 | O701: May | P701: 2014

Sheet Summary
A1: Sales and profit by segment
A2: Source: Financial Sample (Microsoft), Sheet1 · all years
A4: Segment | B4: Units sold | C4: Sales | D4: Profit | E4: Margin
A5: Government | B5: =SUMIFS(Sheet1!$E:$E,Sheet1!$A:$A,$A5) -> 470673.5 | C5: =SUMIFS(Sheet1!$J:$J,Sheet1!$A:$A,$A5) -> 52504261 | D5: =SUMIFS(Sheet1!$L:$L,Sheet1!$A:$A,$A5) -> 11388173 | E5: =IF(C5=0,0,D5/C5) -> 0.21689998
A6: Midmarket | B6: =SUMIFS(Sheet1!$E:$E,Sheet1!$A:$A,$A6) -> 172178 | C6: =SUMIFS(Sheet1!$J:$J,Sheet1!$A:$A,$A6) -> 2381883.1 | D6: =SUMIFS(Sheet1!$L:$L,Sheet1!$A:$A,$A6) -> 660103.07 | E6: =IF(C6=0,0,D6/C6) -> 0.27713496
A7: Channel Partners | B7: =SUMIFS(Sheet1!$E:$E,Sheet1!$A:$A,$A7) -> 161263.5 | C7: =SUMIFS(Sheet1!$J:$J,Sheet1!$A:$A,$A7) -> 1800593.6 | D7: =SUMIFS(Sheet1!$L:$L,Sheet1!$A:$A,$A7) -> 1316803.1 | E7: =IF(C7=0,0,D7/C7) -> 0.73131611
A8: Enterprise | B8: =SUMIFS(Sheet1!$E:$E,Sheet1!$A:$A,$A8) -> 168552 | C8: =SUMIFS(Sheet1!$J:$J,Sheet1!$A:$A,$A8) -> 19611694 | D8: =SUMIFS(Sheet1!$L:$L,Sheet1!$A:$A,$A8) -> -614545.62 | E8: =IF(C8=0,0,D8/C8) -> -0.031335672
A9: Small Business | B9: =SUMIFS(Sheet1!$E:$E,Sheet1!$A:$A,$A9) -> 153139 | C9: =SUMIFS(Sheet1!$J:$J,Sheet1!$A:$A,$A9) -> 42427918 | D9: =SUMIFS(Sheet1!$L:$L,Sheet1!$A:$A,$A9) -> 4143168.5 | E9: =IF(C9=0,0,D9/C9) -> 0.097651939
A10: Total | B10: =SUM(B5:B9) -> 1125806 | C10: =SUM(C5:C9) -> 1.1872635e+08 | D10: =SUM(D5:D9) -> 16893702 | E10: =IF(C10=0,0,D10/C10) -> 0.14229109
A13: Country | B13: Sales | C13: Profit
A14: Canada | B14: =SUMIFS(Sheet1!$J:$J,Sheet1!$B:$B,$A14) -> 24887655 | C14: =SUMIFS(Sheet1!$L:$L,Sheet1!$B:$B,$A14) -> 3529228.9
A15: France | B15: =SUMIFS(Sheet1!$J:$J,Sheet1!$B:$B,$A15) -> 24354172 | C15: =SUMIFS(Sheet1!$L:$L,Sheet1!$B:$B,$A15) -> 3781020.8
A16: Germany | B16: =SUMIFS(Sheet1!$J:$J,Sheet1!$B:$B,$A16) -> 23505341 | C16: =SUMIFS(Sheet1!$L:$L,Sheet1!$B:$B,$A16) -> 3680388.8
A17: Mexico | B17: =SUMIFS(Sheet1!$J:$J,Sheet1!$B:$B,$A17) -> 20949352 | C17: =SUMIFS(Sheet1!$L:$L,Sheet1!$B:$B,$A17) -> 2907523.1
A18: United States of America | B18: =SUMIFS(Sheet1!$J:$J,Sheet1!$B:$B,$A18) -> 25029830 | C18: =SUMIFS(Sheet1!$L:$L,Sheet1!$B:$B,$A18) -> 2995540.7
